{
  "version": 1,
  "timestamp": "2026-06-19T13:52:32.000898Z",
  "data": {
    "transactions": [
      {
        "id": 6446,
        "type": "income",
        "amount": 195.0,
        "category_id": 5,
        "source_id": 1,
        "date": "2021-01-01T00:00:00Z",
        "notes": "SELF"
      },
      {
        "id": 6447,
        "type": "expense",
        "amount": 1500.0,
        "category_id": 5,
        "source_id": 2,
        "date": "2021-01-01T01:59:35Z",
        "notes": "Transferred to Vivek"
      },
      {
        "id": 6448,
        "type": "expense",
        "amount": 5000.0,
        "category_id": 5,
        "source_id": 2,
        "date": "2021-01-01T06:00:37Z",
        "notes": "Transferred to Abi"
      },
      {
        "id": 6449,
        "type": "income",
        "amount": 5.0,
        "category_id": 13,
        "source_id": 2,
        "date": "2021-01-01T06:01:12Z",
        "notes": "Get it From Tez"
      },
      {
        "id": 6450,
        "type": "expense",
        "amount": 5.0,
        "category_id": 5,
        "source_id": 1,
        "date": "2021-01-01T08:55:19Z",
        "notes": "Donated"
      },
      {
        "id": 6451,
        "type": "expense",
        "amount": 10.0,
        "category_id": 5,
        "source_id": 1,
        "date": "2021-01-01T08:56:01Z",
        "notes": "Donated"
      },
      {
        "id": 6452,
        "type": "income",
        "amount": 1500.0,
        "category_id": 5,
        "source_id": 1,
        "date": "2021-01-01T08:57:30Z",
        "notes": "Vivek Withdrawn For Me"
      },
      {
        "id": 6453,
        "type": "income",
        "amount": 5000.0,
        "category_id": 5,
        "source_id": 1,
        "date": "2021-01-01T09:01:26Z",
        "notes": "ATM Withdrawal - Indian - Indian"
      },
      {
        "id": 6454,
        "type": "expense",
        "amount": 3300.0,
        "category_id": 5,
        "source_id": 1,
        "date": "2021-01-01T09:02:58Z",
        "notes": "Cycle For Eniyan"
      },
      {
        "id": 6455,
        "type": "expense",
        "amount": 875.0,
        "category_id": 5,
        "source_id": 1,
        "date": "2021-01-01T23:28:23Z",
        "notes": "Drinks, Snacks & Food"
      },
      {
        "id": 6456,
        "type": "expense",
        "amount": 10.0,
        "category_id": 9,
        "source_id": 1,
        "date": "2021-01-01T23:29:29Z",
        "notes": "Snacks For Shivani & Shreesha"
      },
      {
        "id": 6457,
        "type": "expense",
        "amount": 40000.0,
        "category_id": 20,
        "source_id": 2,
        "date": "2021-01-02T01:38:09Z",
        "notes": "Gave it to Akka"
      },
      {
        "id": 6458,
        "type": "expense",
        "amount": 4974.0,
        "category_id": 5,
        "source_id": 2,
        "date": "2021-01-02T11:20:07Z",
        "notes": "Post Office Deposit"
      },
      {
        "id": 6459,
        "type": "expense",
        "amount": 200.0,
        "category_id": 5,
        "source_id": 1,
        "date": "2021-01-03T10:16:56Z",
        "notes": "Mushroom Fry, Chicken Noodles & Chicken Fried Rice"
      },
      {
        "id": 6460,
        "type": "income",
        "amount": 40029.0,
        "category_id": 5,
        "source_id": 2,
        "date": "2021-01-03T11:11:21Z",
        "notes": "PRABU"
      },
      {
        "id": 6461,
        "type": "expense",
        "amount": 310.0,
        "category_id": 16,
        "source_id": 1,
        "date": "2021-01-03T20:29:41Z",
        "notes": "Mutton, Chicken Biriyani & 65"
      },
      {
        "id": 6462,
        "type": "expense",
        "amount": 90.0,
        "category_id": 12,
        "source_id": 1,
        "date": "2021-01-03T20:44:59Z",
        "notes": "Bike Petrol"
      },
      {
        "id": 6463,
        "type": "income",
        "amount": 2350.0,
        "category_id": 5,
        "source_id": 6,
        "date": "2021-01-03T23:59:59Z",
        "notes": "null"
      },
      {
        "id": 6464,
        "type": "expense",
        "amount": 6000.0,
        "category_id": 5,
        "source_id": 2,
        "date": "2021-01-04T03:51:37Z",
        "notes": "null"
      },
      {
        "id": 6465,
        "type": "expense",
        "amount": 6000.0,
        "category_id": 19,
        "source_id": 2,
        "date": "2021-01-04T10:34:25Z",
        "notes": "Shivani RD"
      },
      {
        "id": 6466,
        "type": "expense",
        "amount": 33.0,
        "category_id": 9,
        "source_id": 1,
        "date": "2021-01-04T20:51:14Z",
        "notes": "Snacks For Akka Family"
      },
      {
        "id": 6467,
        "type": "income",
        "amount": 5200.0,
        "category_id": 5,
        "source_id": 2,
        "date": "2021-01-05T01:55:08Z",
        "notes": "KARTHIKEY"
      },
      {
        "id": 6468,
        "type": "expense",
        "amount": 525.0,
        "category_id": 18,
        "source_id": 1,
        "date": "2021-01-05T13:25:19Z",
        "notes": "Nachi Son Birthday"
      },
      {
        "id": 6469,
        "type": "expense",
        "amount": 120.0,
        "category_id": 12,
        "source_id": 1,
        "date": "2021-01-05T13:26:15Z",
        "notes": "Bike Petrol"
      },
      {
        "id": 6470,
        "type": "expense",
        "amount": 500.0,
        "category_id": 5,
        "source_id": 1,
        "date": "2021-01-05T13:27:40Z",
        "notes": "Gave it To Rajendran Uncle"
      },
      {
        "id": 6471,
        "type": "expense",
        "amount": 4000.0,
        "category_id": 5,
        "source_id": 2,
        "date": "2021-01-07T11:04:32Z",
        "notes": "Gold Chit"
      },
      {
        "id": 6472,
        "type": "expense",
        "amount": 2000.0,
        "category_id": 5,
        "source_id": 2,
        "date": "2021-01-07T11:08:48Z",
        "notes": "Gold Chit Mom - 3 - January Month"
      },
      {
        "id": 6473,
        "type": "expense",
        "amount": 2000.0,
        "category_id": 5,
        "source_id": 2,
        "date": "2021-01-07T11:09:01Z",
        "notes": "Gold Chit Abi - 3 - January Month"
      },
      {
        "id": 6474,
        "type": "expense",
        "amount": 1000.0,
        "category_id": 20,
        "source_id": 2,
        "date": "2021-01-08T04:46:28Z",
        "notes": "Gave it to Karthik Ram JJ"
      },
      {
        "id": 6475,
        "type": "expense",
        "amount": 248.0,
        "category_id": 5,
        "source_id": 2,
        "date": "2021-01-08T12:52:41Z",
        "notes": "Bang Home DTH Recharge"
      },
      {
        "id": 6476,
        "type": "expense",
        "amount": 500.0,
        "category_id": 5,
        "source_id": 1,
        "date": "2021-01-09T01:03:57Z",
        "notes": "5th Check-up : Tablet"
      },
      {
        "id": 6477,
        "type": "expense",
        "amount": 150.0,
        "category_id": 5,
        "source_id": 1,
        "date": "2021-01-09T01:38:10Z",
        "notes": "5th Check-up Doc Fees"
      },
      {
        "id": 6478,
        "type": "expense",
        "amount": 3000.0,
        "category_id": 5,
        "source_id": 1,
        "date": "2021-01-09T01:40:37Z",
        "notes": "5th Check-up : Blood Test & Tablet"
      },
      {
        "id": 6479,
        "type": "expense",
        "amount": 269.0,
        "category_id": 9,
        "source_id": 1,
        "date": "2021-01-09T01:41:48Z",
        "notes": "Snacks From Bakery"
      },
      {
        "id": 6480,
        "type": "expense",
        "amount": 1135.0,
        "category_id": 5,
        "source_id": 3,
        "date": "2021-01-09T01:48:11Z",
        "notes": "Clothes For Abi & Agalya"
      },
      {
        "id": 6481,
        "type": "expense",
        "amount": 1298.0,
        "category_id": 5,
        "source_id": 3,
        "date": "2021-01-09T19:53:07Z",
        "notes": "Clothes For Eniyan & Myself"
      },
      {
        "id": 6482,
        "type": "expense",
        "amount": 1337.0,
        "category_id": 5,
        "source_id": 3,
        "date": "2021-01-09T20:16:36Z",
        "notes": "Clothes For Abi & Agalya"
      },
      {
        "id": 6483,
        "type": "expense",
        "amount": 35.0,
        "category_id": 16,
        "source_id": 1,
        "date": "2021-01-10T01:13:27Z",
        "notes": "Parotta For Abi"
      },
      {
        "id": 6484,
        "type": "expense",
        "amount": 250.0,
        "category_id": 5,
        "source_id": 1,
        "date": "2021-01-10T01:43:39Z",
        "notes": "Gold Repair"
      },
      {
        "id": 6485,
        "type": "income",
        "amount": 1695.0,
        "category_id": 5,
        "source_id": 2,
        "date": "2021-01-10T02:51:23Z",
        "notes": "Ms ABINAY"
      },
      {
        "id": 6486,
        "type": "expense",
        "amount": 100.0,
        "category_id": 5,
        "source_id": 1,
        "date": "2021-01-11T01:02:57Z",
        "notes": "Cakes From Bakery"
      },
      {
        "id": 6487,
        "type": "expense",
        "amount": 150.0,
        "category_id": 5,
        "source_id": 1,
        "date": "2021-01-11T01:11:16Z",
        "notes": "Hospital Visit For Eniyan : Doc Fees"
      },
      {
        "id": 6488,
        "type": "expense",
        "amount": 30.0,
        "category_id": 5,
        "source_id": 1,
        "date": "2021-01-11T01:11:54Z",
        "notes": "Hospital Visit For Eniyan : Ointment"
      },
      {
        "id": 6489,
        "type": "expense",
        "amount": 3400.0,
        "category_id": 5,
        "source_id": 1,
        "date": "2021-01-11T01:12:01Z",
        "notes": "5th Check-up : Blood Test & Scan"
      },
      {
        "id": 6490,
        "type": "expense",
        "amount": 6.0,
        "category_id": 5,
        "source_id": 1,
        "date": "2021-01-11T01:15:23Z",
        "notes": "Gave it to Eniyan"
      },
      {
        "id": 6491,
        "type": "expense",
        "amount": 10000.0,
        "category_id": 5,
        "source_id": 3,
        "date": "2021-01-11T10:19:33Z",
        "notes": "ATM Withdrawal"
      },
      {
        "id": 6492,
        "type": "expense",
        "amount": 6000.0,
        "category_id": 5,
        "source_id": 3,
        "date": "2021-01-11T10:20:13Z",
        "notes": "ATM Withdrawal"
      },
      {
        "id": 6493,
        "type": "expense",
        "amount": 45.0,
        "category_id": 5,
        "source_id": 1,
        "date": "2021-01-13T23:15:30Z",
        "notes": "Vomit Tablets"
      },
      {
        "id": 6494,
        "type": "expense",
        "amount": 1000.0,
        "category_id": 5,
        "source_id": 1,
        "date": "2021-01-13T23:22:31Z",
        "notes": "Jan-21"
      },
      {
        "id": 6495,
        "type": "expense",
        "amount": 10000.0,
        "category_id": 5,
        "source_id": 1,
        "date": "2021-01-13T23:25:08Z",
        "notes": "Gave it to Dad"
      },
      {
        "id": 6496,
        "type": "expense",
        "amount": 25583.0,
        "category_id": 5,
        "source_id": 2,
        "date": "2021-01-14T09:41:03Z",
        "notes": "Paytm/Paytm Pay"
      },
      {
        "id": 6497,
        "type": "expense",
        "amount": 15.0,
        "category_id": 5,
        "source_id": 1,
        "date": "2021-01-14T11:44:11Z",
        "notes": "Gave it to Abi"
      },
      {
        "id": 6498,
        "type": "expense",
        "amount": 130.0,
        "category_id": 5,
        "source_id": 1,
        "date": "2021-01-14T15:54:20Z",
        "notes": "Pongal Kurunthampattu Trip : Bike Petrol"
      },
      {
        "id": 6499,
        "type": "expense",
        "amount": 35.0,
        "category_id": 5,
        "source_id": 1,
        "date": "2021-01-14T15:55:28Z",
        "notes": "Pongal Kurunthampattu Trip : Battery Water"
      },
      {
        "id": 6500,
        "type": "expense",
        "amount": 102.0,
        "category_id": 5,
        "source_id": 1,
        "date": "2021-01-14T15:56:31Z",
        "notes": "Pongal Kurunthampattu Trip : Donated God"
      },
      {
        "id": 6501,
        "type": "expense",
        "amount": 249.0,
        "category_id": 5,
        "source_id": 2,
        "date": "2021-01-15T08:21:16Z",
        "notes": "Recharge For Mother-in-law"
      },
      {
        "id": 6502,
        "type": "expense",
        "amount": 49.0,
        "category_id": 5,
        "source_id": 3,
        "date": "2021-01-15T08:46:52Z",
        "notes": "Recharge For Abi Ammachi"
      },
      {
        "id": 6503,
        "type": "expense",
        "amount": 50.0,
        "category_id": 5,
        "source_id": 1,
        "date": "2021-01-16T22:07:05Z",
        "notes": "Hospital Visit : Doctor Fees"
      },
      {
        "id": 6504,
        "type": "expense",
        "amount": 130.0,
        "category_id": 5,
        "source_id": 1,
        "date": "2021-01-16T22:08:19Z",
        "notes": "Hospital Visit  : Medicine"
      },
      {
        "id": 6505,
        "type": "expense",
        "amount": 17.7,
        "category_id": 5,
        "source_id": 2,
        "date": "2021-01-17T12:10:15Z",
        "notes": "Consolidated Charges for A/c"
      },
      {
        "id": 6506,
        "type": "expense",
        "amount": 150.3,
        "category_id": 5,
        "source_id": 2,
        "date": "2021-01-18T01:19:07Z",
        "notes": "PRABU S/STATE B"
      },
      {
        "id": 6507,
        "type": "income",
        "amount": 25600.0,
        "category_id": 5,
        "source_id": 1,
        "date": "2021-01-18T11:47:17Z",
        "notes": "ATM Withdrawal"
      },
      {
        "id": 6508,
        "type": "expense",
        "amount": 20000.0,
        "category_id": 20,
        "source_id": 1,
        "date": "2021-01-18T11:51:05Z",
        "notes": "Akka"
      },
      {
        "id": 6509,
        "type": "expense",
        "amount": 1120.0,
        "category_id": 18,
        "source_id": 1,
        "date": "2021-01-19T08:39:05Z",
        "notes": "Shivani Birthday Gift : Teddy Bear"
      },
      {
        "id": 6510,
        "type": "expense",
        "amount": 140.0,
        "category_id": 12,
        "source_id": 1,
        "date": "2021-01-19T08:40:03Z",
        "notes": "Bike Petrol"
      },
      {
        "id": 6511,
        "type": "expense",
        "amount": 22499.0,
        "category_id": 5,
        "source_id": 3,
        "date": "2021-01-20T09:57:36Z",
        "notes": "Akka Housewarming : Tv - One Plus"
      },
      {
        "id": 6512,
        "type": "expense",
        "amount": 558.1,
        "category_id": 18,
        "source_id": 3,
        "date": "2021-01-20T15:15:39Z",
        "notes": "Sreesha Birthday Gift : Remote Car"
      },
      {
        "id": 6513,
        "type": "expense",
        "amount": 90.0,
        "category_id": 9,
        "source_id": 1,
        "date": "2021-01-20T23:32:51Z",
        "notes": "Corn"
      },
      {
        "id": 6514,
        "type": "expense",
        "amount": 199.0,
        "category_id": 5,
        "source_id": 2,
        "date": "2021-01-23T02:51:35Z",
        "notes": "Pdkt Home DTH Recharge"
      },
      {
        "id": 6515,
        "type": "income",
        "amount": 15.0,
        "category_id": 13,
        "source_id": 2,
        "date": "2021-01-23T02:51:47Z",
        "notes": "Get it From Paytm"
      },
      {
        "id": 6516,
        "type": "expense",
        "amount": 316.0,
        "category_id": 5,
        "source_id": 2,
        "date": "2021-01-23T03:08:54Z",
        "notes": "PRABU S/STATE B"
      },
      {
        "id": 6517,
        "type": "expense",
        "amount": 10.0,
        "category_id": 9,
        "source_id": 1,
        "date": "2021-01-23T09:59:18Z",
        "notes": "Snacks For Shreesha"
      },
      {
        "id": 6518,
        "type": "expense",
        "amount": 6.0,
        "category_id": 5,
        "source_id": 1,
        "date": "2021-01-23T10:00:48Z",
        "notes": "Akka Housewarming : Tv - One Plus Installation"
      },
      {
        "id": 6519,
        "type": "expense",
        "amount": 10000.0,
        "category_id": 20,
        "source_id": 2,
        "date": "2021-01-24T03:21:29Z",
        "notes": "Akka"
      },
      {
        "id": 6520,
        "type": "income",
        "amount": 3.0,
        "category_id": 13,
        "source_id": 2,
        "date": "2021-01-24T03:21:57Z",
        "notes": "Get it From Tez"
      },
      {
        "id": 6521,
        "type": "expense",
        "amount": 3000.0,
        "category_id": 20,
        "source_id": 2,
        "date": "2021-01-24T03:53:22Z",
        "notes": "Akka"
      },
      {
        "id": 6522,
        "type": "expense",
        "amount": 20.0,
        "category_id": 5,
        "source_id": 2,
        "date": "2021-01-24T04:43:15Z",
        "notes": "Akka Housewarming : Light Screw"
      },
      {
        "id": 6523,
        "type": "expense",
        "amount": 10.0,
        "category_id": 5,
        "source_id": 2,
        "date": "2021-01-24T04:56:42Z",
        "notes": "Akka Housewarming : Light Screw"
      },
      {
        "id": 6524,
        "type": "expense",
        "amount": 160.0,
        "category_id": 12,
        "source_id": 1,
        "date": "2021-01-24T08:47:48Z",
        "notes": "Bik Petrol"
      },
      {
        "id": 6525,
        "type": "expense",
        "amount": 585.0,
        "category_id": 5,
        "source_id": 1,
        "date": "2021-01-24T09:57:58Z",
        "notes": "Drinks"
      },
      {
        "id": 6526,
        "type": "expense",
        "amount": 230.0,
        "category_id": 5,
        "source_id": 3,
        "date": "2021-01-24T10:06:56Z",
        "notes": "Pears Soap"
      },
      {
        "id": 6527,
        "type": "expense",
        "amount": 201.0,
        "category_id": 5,
        "source_id": 3,
        "date": "2021-01-24T10:07:46Z",
        "notes": "Cinthol Soap"
      },
      {
        "id": 6528,
        "type": "expense",
        "amount": 81.0,
        "category_id": 9,
        "source_id": 3,
        "date": "2021-01-24T10:08:23Z",
        "notes": "Milk Shakes"
      },
      {
        "id": 6529,
        "type": "expense",
        "amount": 189.0,
        "category_id": 5,
        "source_id": 3,
        "date": "2021-01-24T10:09:39Z",
        "notes": "Sensodyne Paste"
      },
      {
        "id": 6530,
        "type": "expense",
        "amount": 60.0,
        "category_id": 9,
        "source_id": 3,
        "date": "2021-01-24T10:10:09Z",
        "notes": "Mixture From Super Market"
      },
      {
        "id": 6531,
        "type": "expense",
        "amount": 761.0,
        "category_id": 5,
        "source_id": 3,
        "date": "2021-01-24T17:24:29Z",
        "notes": "Shopping in Jana Priya"
      },
      {
        "id": 6532,
        "type": "expense",
        "amount": 83.0,
        "category_id": 5,
        "source_id": 1,
        "date": "2021-01-25T00:09:57Z",
        "notes": "2nd Service"
      },
      {
        "id": 6533,
        "type": "expense",
        "amount": 283.0,
        "category_id": 5,
        "source_id": 3,
        "date": "2021-01-25T09:47:02Z",
        "notes": "Purchased Pampers For Agalya"
      },
      {
        "id": 6534,
        "type": "expense",
        "amount": 73.0,
        "category_id": 5,
        "source_id": 2,
        "date": "2021-01-26T10:30:00Z",
        "notes": "PRABU S/STATE B"
      },
      {
        "id": 6535,
        "type": "income",
        "amount": 73.0,
        "category_id": 5,
        "source_id": 3,
        "date": "2021-01-26T11:00:42Z",
        "notes": "PRABU"
      },
      {
        "id": 6536,
        "type": "expense",
        "amount": 1303.0,
        "category_id": 5,
        "source_id": 3,
        "date": "2021-01-26T12:30:25Z",
        "notes": "Clothes for Abi"
      },
      {
        "id": 6537,
        "type": "expense",
        "amount": 650.0,
        "category_id": 5,
        "source_id": 1,
        "date": "2021-01-26T20:12:48Z",
        "notes": "Bangalore SetTop Box Repair & Recharge"
      },
      {
        "id": 6538,
        "type": "expense",
        "amount": 6.0,
        "category_id": 5,
        "source_id": 1,
        "date": "2021-01-26T23:55:35Z",
        "notes": "Gave it to Eniyan"
      },
      {
        "id": 6539,
        "type": "expense",
        "amount": 3599.0,
        "category_id": 5,
        "source_id": 3,
        "date": "2021-01-27T00:02:12Z",
        "notes": "Purchased Gas Stove For Akka"
      },
      {
        "id": 6540,
        "type": "expense",
        "amount": 50.0,
        "category_id": 5,
        "source_id": 1,
        "date": "2021-01-27T14:54:23Z",
        "notes": "Gave it to Abi"
      },
      {
        "id": 6541,
        "type": "income",
        "amount": 3600.0,
        "category_id": 5,
        "source_id": 1,
        "date": "2021-01-27T16:28:21Z",
        "notes": "ATM Withdrawal"
      },
      {
        "id": 6542,
        "type": "expense",
        "amount": 120.0,
        "category_id": 12,
        "source_id": 1,
        "date": "2021-01-27T16:31:18Z",
        "notes": "Bike Petrol"
      },
      {
        "id": 6543,
        "type": "expense",
        "amount": 25.0,
        "category_id": 9,
        "source_id": 1,
        "date": "2021-01-27T16:55:29Z",
        "notes": "Chocolate & Snacks For Kids"
      },
      {
        "id": 6544,
        "type": "expense",
        "amount": 175.0,
        "category_id": 5,
        "source_id": 1,
        "date": "2021-01-27T16:56:42Z",
        "notes": "Snacks From Bakery For Rajendran Uncle Family"
      },
      {
        "id": 6545,
        "type": "expense",
        "amount": 30.0,
        "category_id": 5,
        "source_id": 1,
        "date": "2021-01-27T16:59:47Z",
        "notes": "Gave it to Shivagami Aunty"
      },
      {
        "id": 6546,
        "type": "expense",
        "amount": 90.0,
        "category_id": 5,
        "source_id": 1,
        "date": "2021-01-27T17:01:52Z",
        "notes": "Bike Petrol For Akka"
      },
      {
        "id": 6547,
        "type": "expense",
        "amount": 230.0,
        "category_id": 22,
        "source_id": 1,
        "date": "2021-01-27T19:11:44Z",
        "notes": "Kids Gandhi Park : Games & Snacks"
      },
      {
        "id": 6548,
        "type": "expense",
        "amount": 399.0,
        "category_id": 11,
        "source_id": 2,
        "date": "2021-01-28T08:46:50Z",
        "notes": "Recharge For Abi"
      },
      {
        "id": 6549,
        "type": "income",
        "amount": 72323.0,
        "category_id": 5,
        "source_id": 2,
        "date": "2021-01-30T05:43:58Z",
        "notes": "January Month"
      },
      {
        "id": 6550,
        "type": "expense",
        "amount": 13280.0,
        "category_id": 5,
        "source_id": 2,
        "date": "2021-01-30T06:00:57Z",
        "notes": "AMAZON/Axis Bank"
      },
      {
        "id": 6551,
        "type": "expense",
        "amount": 4.0,
        "category_id": 5,
        "source_id": 1,
        "date": "2021-01-30T10:44:39Z",
        "notes": "Gave it to Eniyan"
      },
      {
        "id": 6552,
        "type": "expense",
        "amount": 6.0,
        "category_id": 5,
        "source_id": 1,
        "date": "2021-01-30T14:47:53Z",
        "notes": "Bank Documents Xerox"
      },
      {
        "id": 6553,
        "type": "expense",
        "amount": 50.0,
        "category_id": 5,
        "source_id": 1,
        "date": "2021-01-30T14:48:59Z",
        "notes": "Ration Card Abi Name Remove"
      },
      {
        "id": 6554,
        "type": "expense",
        "amount": 20.0,
        "category_id": 9,
        "source_id": 1,
        "date": "2021-01-30T14:50:16Z",
        "notes": "Snacks For Kids"
      },
      {
        "id": 6555,
        "type": "expense",
        "amount": 350.0,
        "category_id": 5,
        "source_id": 1,
        "date": "2021-01-30T20:05:03Z",
        "notes": "Drinks"
      },
      {
        "id": 6556,
        "type": "expense",
        "amount": 150.0,
        "category_id": 16,
        "source_id": 1,
        "date": "2021-01-30T20:07:57Z",
        "notes": "Chicken 65"
      },
      {
        "id": 6557,
        "type": "expense",
        "amount": 20000.0,
        "category_id": 5,
        "source_id": 2,
        "date": "2021-01-31T06:06:28Z",
        "notes": "ARUMUGAM"
      },
      {
        "id": 6558,
        "type": "income",
        "amount": 4.0,
        "category_id": 13,
        "source_id": 2,
        "date": "2021-01-31T06:07:03Z",
        "notes": "Get it From Tez"
      },
      {
        "id": 6559,
        "type": "income",
        "amount": 3.0,
        "category_id": 13,
        "source_id": 2,
        "date": "2021-01-31T06:07:08Z",
        "notes": "Get it From Tez"
      },
      {
        "id": 6560,
        "type": "income",
        "amount": 13280.0,
        "category_id": 5,
        "source_id": 3,
        "date": "2021-01-31T07:23:42Z",
        "notes": "SBI Credit Card Bill Paid"
      },
      {
        "id": 6561,
        "type": "expense",
        "amount": 170.0,
        "category_id": 12,
        "source_id": 1,
        "date": "2021-01-31T09:00:43Z",
        "notes": "Bike Petrol"
      },
      {
        "id": 6562,
        "type": "expense",
        "amount": 50.0,
        "category_id": 9,
        "source_id": 1,
        "date": "2021-01-31T09:02:06Z",
        "notes": "Snacks For Kids"
      },
      {
        "id": 6563,
        "type": "expense",
        "amount": 30.0,
        "category_id": 5,
        "source_id": 1,
        "date": "2021-01-31T09:03:56Z",
        "notes": "Vadai"
      },
      {
        "id": 6564,
        "type": "expense",
        "amount": 60.0,
        "category_id": 5,
        "source_id": 1,
        "date": "2021-01-31T09:07:05Z",
        "notes": "Chicken 65"
      },
      {
        "id": 6565,
        "type": "expense",
        "amount": 550.0,
        "category_id": 5,
        "source_id": 1,
        "date": "2021-01-31T09:12:49Z",
        "notes": "Akka Housewarming : Ice Cream & Plates"
      },
      {
        "id": 6566,
        "type": "expense",
        "amount": 500.0,
        "category_id": 5,
        "source_id": 1,
        "date": "2021-01-31T10:42:29Z",
        "notes": "Gave it to Akka"
      },
      {
        "id": 6567,
        "type": "expense",
        "amount": 120.0,
        "category_id": 5,
        "source_id": 1,
        "date": "2021-01-31T10:44:53Z",
        "notes": "Cool Drinks, Cigarette : & Snacks"
      },
      {
        "id": 6568,
        "type": "expense",
        "amount": 890.0,
        "category_id": 5,
        "source_id": 1,
        "date": "2021-01-31T23:59:59Z",
        "notes": "To Feb"
      }
    ],
    "categories": [
      {
        "id": 1,
        "name": "Groceries",
        "type": "expense",
        "icon": "cart",
        "color": "#F97316"
      },
      {
        "id": 2,
        "name": "Rent",
        "type": "expense",
        "icon": "home-account",
        "color": "#3B82F6"
      },
      {
        "id": 3,
        "name": "Utilities",
        "type": "expense",
        "icon": "lightning-bolt",
        "color": "#64748B"
      },
      {
        "id": 4,
        "name": "Salary",
        "type": "income",
        "icon": "cash-multiple",
        "color": "#16A34A"
      },
      {
        "id": 5,
        "name": "Misc",
        "type": "expense",
        "icon": "dots-horizontal",
        "color": "#9CA3AF"
      },
      {
        "id": 6,
        "name": "DTH",
        "type": "expense",
        "icon": "television-play",
        "color": "#8B5CF6"
      },
      {
        "id": 9,
        "name": "Snacks",
        "type": "expense",
        "icon": "food-variant",
        "color": "#FBBF24"
      },
      {
        "id": 10,
        "name": "Wallet Transfer",
        "type": "expense",
        "icon": "swap-horizontal",
        "color": "#6366F1"
      },
      {
        "id": 11,
        "name": "Mobile Recharge",
        "type": "expense",
        "icon": "cellphone",
        "color": "#0EA5E9"
      },
      {
        "id": 12,
        "name": "Bike / Vehicle",
        "type": "expense",
        "icon": "motorbike",
        "color": "#DC2626"
      },
      {
        "id": 13,
        "name": "Money Received",
        "type": "income",
        "icon": "arrow-down-bold-circle",
        "color": "#10B981"
      },
      {
        "id": 14,
        "name": "Interest",
        "type": "income",
        "icon": "percent",
        "color": "#22C55E"
      },
      {
        "id": 15,
        "name": "Money Given",
        "type": "expense",
        "icon": "arrow-up-bold-circle",
        "color": "#EF4444"
      },
      {
        "id": 16,
        "name": "Food & Dining",
        "type": "expense",
        "icon": "silverware-fork-knife",
        "color": "#F59E0B"
      },
      {
        "id": 17,
        "name": "Family",
        "type": "expense",
        "icon": "account-group",
        "color": "#F43F5E"
      },
      {
        "id": 18,
        "name": "Gifts",
        "type": "expense",
        "icon": "gift",
        "color": "#EC4899"
      },
      {
        "id": 19,
        "name": "Savings",
        "type": "expense",
        "icon": "piggy-bank",
        "color": "#059669"
      },
      {
        "id": 20,
        "name": "Loan / EMI",
        "type": "expense",
        "icon": "bank-transfer",
        "color": "#B91C1C"
      },
      {
        "id": 21,
        "name": "Transport",
        "type": "expense",
        "icon": "bus",
        "color": "#14B8A6"
      },
      {
        "id": 22,
        "name": "Entertainment",
        "type": "expense",
        "icon": "movie-open",
        "color": "#7C3AED"
      },
      {
        "id": 23,
        "name": "Donations",
        "type": "expense",
        "icon": "hand-heart",
        "color": "#22C55E"
      },
      {
        "id": 24,
        "name": "Home Improvement",
        "type": "expense",
        "icon": "hammer-wrench",
        "color": "#A16207"
      },
      {
        "id": 25,
        "name": "Printing & Stationery",
        "type": "expense",
        "icon": "printer",
        "color": "#6B7280"
      },
      {
        "id": 26,
        "name": "Bank Charges",
        "type": "expense",
        "icon": "bank",
        "color": "#374151"
      }
    ],
    "sources": [
      {
        "id": 1,
        "name": "Cash Spend",
        "initial_balance": 0,
        "icon": "bank",
        "color": "#6366F1"
      },
      {
        "id": 2,
        "name": "Axis",
        "initial_balance": 0,
        "icon": "bank",
        "color": "#6366F1"
      },
      {
        "id": 3,
        "name": "SBI Group",
        "initial_balance": 0,
        "icon": "bank",
        "color": "#6366F1"
      },
      {
        "id": 4,
        "name": "Airtel Payments",
        "initial_balance": 0,
        "icon": "bank",
        "color": "#6366F1"
      },
      {
        "id": 5,
        "name": "Paytm",
        "initial_balance": 0,
        "icon": "bank",
        "color": "#6366F1"
      },
      {
        "id": 6,
        "name": "Unknown",
        "initial_balance": 0,
        "icon": "bank",
        "color": "#6366F1"
      },
      {
        "id": 7,
        "name": "Vijaya",
        "initial_balance": 0,
        "icon": "bank",
        "color": "#6366F1"
      },
      {
        "id": 8,
        "name": "Freecharge",
        "initial_balance": 0,
        "icon": "bank",
        "color": "#6366F1"
      },
      {
        "id": 9,
        "name": "City Union",
        "initial_balance": 0,
        "icon": "bank",
        "color": "#6366F1"
      },
      {
        "id": 10,
        "name": "MOBIKWIK",
        "initial_balance": 0,
        "icon": "bank",
        "color": "#6366F1"
      },
      {
        "id": 11,
        "name": "BOB",
        "initial_balance": 0,
        "icon": "bank",
        "color": "#6366F1"
      },
      {
        "id": 12,
        "name": "HDFC",
        "initial_balance": 0,
        "icon": "bank",
        "color": "#6366F1"
      },
      {
        "id": 13,
        "name": "Other",
        "initial_balance": 0,
        "icon": "bank",
        "color": "#6366F1"
      }
    ],
    "budgets": [],
    "bills": []
  }
}